{"asset": {                "version": "0.0",                "gltfUpAxis": "Y"            },            "geometricError":100.000000,"root": {                "transform": [-0.969964,-0.243248,0.000000,0.000000,0.123017,-0.490539,0.862693,0.000000,-0.209486,0.835337,0.508259,0.000000,-1337286.973369,5332509.468785,3222830.619095,1],                "boundingVolume": {                    "region": [1.816433,0.533100,1.816585,0.533224,0.000000,87.000000]},"geometricError": 100.000000,                        "refine": "REPLACE",                        "content": {                            "uri": "./tile/5/11/6.b3dm"}}}