{"asset": {                "version": "0.0",                "gltfUpAxis": "Y"            },            "geometricError":100.000000,"root": {                "transform": [-0.969938,-0.243353,0.000000,0.000000,0.123322,-0.491530,0.862085,0.000000,-0.209427,0.834720,0.509296,0.000000,-1336916.331981,5328589.555966,3229416.750940,1],                "boundingVolume": {                    "region": [1.816602,0.534355,1.816632,0.534378,0.000000,9.000000]},"geometricError": 100.000000,                        "refine": "REPLACE",                        "content": {                            "uri": "./tile/5/12/16.b3dm"}}}