{"asset": {                "version": "0.0",                "gltfUpAxis": "Y"            },            "geometricError":100.000000,"root": {                "transform": [-0.969776,-0.243998,0.000000,0.000000,0.123488,-0.490806,0.862473,0.000000,-0.210078,0.834961,0.508633,0.000000,-1341069.453041,5330110.340078,3225210.681276,1],                "boundingVolume": {                    "region": [1.817276,0.533589,1.817289,0.533605,0.000000,8.000000]},"geometricError": 100.000000,                        "refine": "REPLACE",                        "content": {                            "uri": "./tile/5/16/10.b3dm"}}}