{"asset": {                "version": "0.0",                "gltfUpAxis": "Y"            },            "geometricError":100.000000,"root": {                "transform": [-0.969495,-0.245112,0.000000,0.000000,0.124003,-0.490469,0.862591,0.000000,-0.211066,0.834834,0.508432,0.000000,-1347376.775227,5329298.294306,3223932.154936,1],                "boundingVolume": {                    "region": [1.818378,0.533341,1.818485,0.533385,0.000000,8.000000]},"geometricError": 100.000000,                        "refine": "REPLACE",                        "content": {                            "uri": "./tile/5/23/8.b3dm"}}}