{"asset": {                "version": "0.0",                "gltfUpAxis": "Y"            },            "geometricError":100.000000,"root": {                "transform": [-0.969737,-0.244153,0.000000,0.000000,0.123859,-0.491950,0.861768,0.000000,-0.210038,0.834238,0.509835,0.000000,-1340818.174770,5325517.438794,3232841.776094,1],                "boundingVolume": {                    "region": [1.817417,0.534960,1.817467,0.535025,0.000000,3.000000]},"geometricError": 100.000000,                        "refine": "REPLACE",                        "content": {                            "uri": "./tile/5/17/21.b3dm"}}}