{"asset": {                "version": "0.0",                "gltfUpAxis": "Y"            },            "geometricError":100.000000,"root": {                "transform": [-0.969997,-0.243116,0.000000,0.000000,0.123002,-0.490759,0.862570,0.000000,-0.209342,0.835246,0.508469,0.000000,-1336371.292118,5331927.277898,3224164.419358,1],                "boundingVolume": {                    "region": [1.816309,0.533342,1.816437,0.533470,0.000000,153.000000]},"geometricError": 100.000000,                        "refine": "REPLACE",                        "content": {                            "uri": "./tile/5/10/8.b3dm"}}}