{"asset": {                "version": "0.0",                "gltfUpAxis": "Y"            },            "geometricError":100.000000,"root": {                "transform": [-0.970163,-0.242452,0.000000,0.000000,0.123033,-0.492310,0.861681,0.000000,-0.208554,0.834519,0.509984,0.000000,-1331343.054329,5327315.962920,3233787.931464,1],                "boundingVolume": {                    "region": [1.815665,0.535151,1.815713,0.535180,0.000000,15.000000]},"geometricError": 100.000000,                        "refine": "REPLACE",                        "content": {                            "uri": "./tile/5/6/22.b3dm"}}}